st_tailwind/__init__.py
st_tailwind/const.py
st_tailwind/core.py
st_tailwind/resources/__init__.py
st_tailwind/resources/frontend/__init__.py
st_tailwind/resources/frontend/build.js
st_tailwind/resources/frontend/init.js
st_tailwind/resources/frontend/init.min.js
st_tailwind/resources/frontend/init.min.js.map
st_tailwind/resources/frontend/package.json
st_tailwind-1.2.1.dist-info/METADATA
st_tailwind-1.2.1.dist-info/WHEEL
st_tailwind-1.2.1.dist-info/top_level.txt
st_tailwind-1.2.1.dist-info/RECORD
