Metadata-Version: 2.1
Name: st_tailwind
Version: 1.2.1
Summary: Python tailwind toolkit - Injected with JS
Author-email: "rafael.choinhet" <choinhet@gmail.com>
License: MIT
Requires-Python: >=3.9.10
Requires-Dist: streamlit>=1.38.0
